{
    "order_263": {
        "to": 22, 
        "from": 32, 
        "supply": 8.721
    }, 
    "order_241": {
        "to": 21, 
        "from": 27, 
        "supply": 1.311
    }, 
    "order_246": {
        "to": 42, 
        "from": 11, 
        "supply": 6.914
    }, 
    "order_262": {
        "to": 3, 
        "from": 21, 
        "supply": 5.004
    }, 
    "order_247": {
        "to": 4, 
        "from": 48, 
        "supply": 4.645
    }, 
    "order_244": {
        "to": 3, 
        "from": 1, 
        "supply": 9.35
    }, 
    "order_209": {
        "to": 24, 
        "from": 37, 
        "supply": 5.462
    }, 
    "order_276": {
        "to": 30, 
        "from": 44, 
        "supply": 3.92
    }, 
    "order_264": {
        "to": 20, 
        "from": 47, 
        "supply": 6.75
    }, 
    "order_152": {
        "to": 4, 
        "from": 10, 
        "supply": 9.523
    }, 
    "order_153": {
        "to": 41, 
        "from": 31, 
        "supply": 4.909
    }, 
    "order_150": {
        "to": 2, 
        "from": 34, 
        "supply": 2.916
    }, 
    "order_151": {
        "to": 42, 
        "from": 38, 
        "supply": 7.137
    }, 
    "order_156": {
        "to": 31, 
        "from": 32, 
        "supply": 9.012
    }, 
    "order_157": {
        "to": 36, 
        "from": 28, 
        "supply": 3.265
    }, 
    "order_154": {
        "to": 13, 
        "from": 15, 
        "supply": 8.723
    }, 
    "order_155": {
        "to": 20, 
        "from": 12, 
        "supply": 2.313
    }, 
    "order_268": {
        "to": 7, 
        "from": 36, 
        "supply": 1.442
    }, 
    "order_269": {
        "to": 16, 
        "from": 34, 
        "supply": 1.777
    }, 
    "order_158": {
        "to": 14, 
        "from": 32, 
        "supply": 3.976
    }, 
    "order_159": {
        "to": 28, 
        "from": 30, 
        "supply": 6.771
    }, 
    "order_38": {
        "to": 9, 
        "from": 32, 
        "supply": 7.868
    }, 
    "order_39": {
        "to": 6, 
        "from": 21, 
        "supply": 3.085
    }, 
    "order_32": {
        "to": 9, 
        "from": 20, 
        "supply": 8.188
    }, 
    "order_33": {
        "to": 40, 
        "from": 25, 
        "supply": 6.636
    }, 
    "order_30": {
        "to": 31, 
        "from": 21, 
        "supply": 5.599
    }, 
    "order_31": {
        "to": 16, 
        "from": 7, 
        "supply": 8.036
    }, 
    "order_36": {
        "to": 5, 
        "from": 9, 
        "supply": 1.796
    }, 
    "order_37": {
        "to": 17, 
        "from": 49, 
        "supply": 6.99
    }, 
    "order_34": {
        "to": 41, 
        "from": 16, 
        "supply": 8.079
    }, 
    "order_35": {
        "to": 36, 
        "from": 2, 
        "supply": 3.182
    }, 
    "order_58": {
        "to": 17, 
        "from": 47, 
        "supply": 9.889
    }, 
    "order_59": {
        "to": 5, 
        "from": 41, 
        "supply": 9.181
    }, 
    "order_299": {
        "to": 46, 
        "from": 35, 
        "supply": 6.017
    }, 
    "order_245": {
        "to": 9, 
        "from": 29, 
        "supply": 6.014
    }, 
    "order_214": {
        "to": 6, 
        "from": 11, 
        "supply": 5.542
    }, 
    "order_50": {
        "to": 3, 
        "from": 2, 
        "supply": 5.067
    }, 
    "order_51": {
        "to": 5, 
        "from": 25, 
        "supply": 7.966
    }, 
    "order_52": {
        "to": 40, 
        "from": 18, 
        "supply": 8.986
    }, 
    "order_53": {
        "to": 5, 
        "from": 33, 
        "supply": 9.002
    }, 
    "order_54": {
        "to": 47, 
        "from": 23, 
        "supply": 6.97
    }, 
    "order_55": {
        "to": 41, 
        "from": 33, 
        "supply": 1.943
    }, 
    "order_56": {
        "to": 17, 
        "from": 13, 
        "supply": 1.024
    }, 
    "order_57": {
        "to": 16, 
        "from": 12, 
        "supply": 6.445
    }, 
    "order_235": {
        "to": 31, 
        "from": 27, 
        "supply": 7.951
    }, 
    "order_216": {
        "to": 29, 
        "from": 5, 
        "supply": 8.095
    }, 
    "order_211": {
        "to": 38, 
        "from": 13, 
        "supply": 4.713
    }, 
    "order_279": {
        "to": 49, 
        "from": 35, 
        "supply": 1.416
    }, 
    "order_210": {
        "to": 35, 
        "from": 7, 
        "supply": 1.87
    }, 
    "order_167": {
        "to": 5, 
        "from": 10, 
        "supply": 9.953
    }, 
    "order_166": {
        "to": 35, 
        "from": 49, 
        "supply": 2.378
    }, 
    "order_165": {
        "to": 25, 
        "from": 7, 
        "supply": 8.036
    }, 
    "order_164": {
        "to": 41, 
        "from": 2, 
        "supply": 1.372
    }, 
    "order_163": {
        "to": 12, 
        "from": 19, 
        "supply": 5.91
    }, 
    "order_162": {
        "to": 6, 
        "from": 30, 
        "supply": 1.565
    }, 
    "order_161": {
        "to": 22, 
        "from": 43, 
        "supply": 5.731
    }, 
    "order_160": {
        "to": 13, 
        "from": 35, 
        "supply": 6.868
    }, 
    "order_212": {
        "to": 47, 
        "from": 0, 
        "supply": 9.233
    }, 
    "order_219": {
        "to": 5, 
        "from": 17, 
        "supply": 5.798
    }, 
    "order_218": {
        "to": 32, 
        "from": 28, 
        "supply": 9.708
    }, 
    "order_169": {
        "to": 46, 
        "from": 24, 
        "supply": 6.279
    }, 
    "order_168": {
        "to": 5, 
        "from": 37, 
        "supply": 9.127
    }, 
    "order_29": {
        "to": 14, 
        "from": 20, 
        "supply": 6.558
    }, 
    "order_28": {
        "to": 20, 
        "from": 24, 
        "supply": 8.293
    }, 
    "order_25": {
        "to": 5, 
        "from": 30, 
        "supply": 3.551
    }, 
    "order_24": {
        "to": 47, 
        "from": 4, 
        "supply": 4.133
    }, 
    "order_27": {
        "to": 36, 
        "from": 14, 
        "supply": 7.695
    }, 
    "order_26": {
        "to": 24, 
        "from": 23, 
        "supply": 9.483
    }, 
    "order_21": {
        "to": 40, 
        "from": 45, 
        "supply": 5.488
    }, 
    "order_20": {
        "to": 43, 
        "from": 23, 
        "supply": 5.402
    }, 
    "order_23": {
        "to": 17, 
        "from": 41, 
        "supply": 6.981
    }, 
    "order_22": {
        "to": 12, 
        "from": 3, 
        "supply": 9.191
    }, 
    "order_49": {
        "to": 19, 
        "from": 30, 
        "supply": 7.577
    }, 
    "order_48": {
        "to": 18, 
        "from": 30, 
        "supply": 7.865
    }, 
    "order_288": {
        "to": 36, 
        "from": 6, 
        "supply": 3.056
    }, 
    "order_289": {
        "to": 47, 
        "from": 5, 
        "supply": 8.316
    }, 
    "order_43": {
        "to": 38, 
        "from": 40, 
        "supply": 2.647
    }, 
    "order_42": {
        "to": 4, 
        "from": 23, 
        "supply": 1.566
    }, 
    "order_41": {
        "to": 0, 
        "from": 23, 
        "supply": 7.544
    }, 
    "order_40": {
        "to": 4, 
        "from": 6, 
        "supply": 3.848
    }, 
    "order_47": {
        "to": 8, 
        "from": 27, 
        "supply": 7.785
    }, 
    "order_46": {
        "to": 2, 
        "from": 40, 
        "supply": 3.401
    }, 
    "order_45": {
        "to": 37, 
        "from": 40, 
        "supply": 8.43
    }, 
    "order_44": {
        "to": 31, 
        "from": 29, 
        "supply": 2.667
    }, 
    "order_178": {
        "to": 14, 
        "from": 26, 
        "supply": 3.504
    }, 
    "order_179": {
        "to": 32, 
        "from": 43, 
        "supply": 3.166
    }, 
    "order_225": {
        "to": 21, 
        "from": 10, 
        "supply": 1.298
    }, 
    "order_170": {
        "to": 18, 
        "from": 44, 
        "supply": 7.047
    }, 
    "order_171": {
        "to": 46, 
        "from": 34, 
        "supply": 8.264
    }, 
    "order_172": {
        "to": 28, 
        "from": 44, 
        "supply": 9.936
    }, 
    "order_173": {
        "to": 49, 
        "from": 12, 
        "supply": 5.282
    }, 
    "order_174": {
        "to": 27, 
        "from": 9, 
        "supply": 2.658
    }, 
    "order_175": {
        "to": 37, 
        "from": 11, 
        "supply": 6.404
    }, 
    "order_176": {
        "to": 8, 
        "from": 36, 
        "supply": 7.412
    }, 
    "order_177": {
        "to": 23, 
        "from": 7, 
        "supply": 7.902
    }, 
    "order_206": {
        "to": 29, 
        "from": 26, 
        "supply": 5.729
    }, 
    "order_207": {
        "to": 12, 
        "from": 2, 
        "supply": 1.637
    }, 
    "order_204": {
        "to": 34, 
        "from": 11, 
        "supply": 9.669
    }, 
    "order_205": {
        "to": 46, 
        "from": 48, 
        "supply": 2.297
    }, 
    "order_202": {
        "to": 26, 
        "from": 15, 
        "supply": 9.365
    }, 
    "order_203": {
        "to": 3, 
        "from": 20, 
        "supply": 9.684
    }, 
    "order_200": {
        "to": 32, 
        "from": 2, 
        "supply": 6.945
    }, 
    "order_201": {
        "to": 34, 
        "from": 46, 
        "supply": 8.793
    }, 
    "order_287": {
        "to": 25, 
        "from": 27, 
        "supply": 3.459
    }, 
    "order_220": {
        "to": 20, 
        "from": 43, 
        "supply": 4.529
    }, 
    "order_208": {
        "to": 22, 
        "from": 6, 
        "supply": 9.148
    }, 
    "order_113": {
        "to": 13, 
        "from": 22, 
        "supply": 4.927
    }, 
    "order_265": {
        "to": 33, 
        "from": 0, 
        "supply": 4.783
    }, 
    "order_222": {
        "to": 18, 
        "from": 6, 
        "supply": 6.154
    }, 
    "order_223": {
        "to": 33, 
        "from": 26, 
        "supply": 4.094
    }, 
    "order_260": {
        "to": 42, 
        "from": 33, 
        "supply": 3.094
    }, 
    "order_78": {
        "to": 26, 
        "from": 37, 
        "supply": 9.685
    }, 
    "order_79": {
        "to": 40, 
        "from": 12, 
        "supply": 1.215
    }, 
    "order_76": {
        "to": 36, 
        "from": 18, 
        "supply": 5.647
    }, 
    "order_77": {
        "to": 28, 
        "from": 23, 
        "supply": 3.364
    }, 
    "order_74": {
        "to": 24, 
        "from": 49, 
        "supply": 2.904
    }, 
    "order_75": {
        "to": 23, 
        "from": 46, 
        "supply": 3.402
    }, 
    "order_72": {
        "to": 27, 
        "from": 3, 
        "supply": 4.674
    }, 
    "order_73": {
        "to": 33, 
        "from": 49, 
        "supply": 8.494
    }, 
    "order_70": {
        "to": 40, 
        "from": 20, 
        "supply": 2.477
    }, 
    "order_71": {
        "to": 1, 
        "from": 20, 
        "supply": 1.291
    }, 
    "order_2": {
        "to": 44, 
        "from": 37, 
        "supply": 5.5
    }, 
    "order_3": {
        "to": 5, 
        "from": 21, 
        "supply": 4.94
    }, 
    "order_0": {
        "to": 12, 
        "from": 17, 
        "supply": 3.729
    }, 
    "order_1": {
        "to": 9, 
        "from": 14, 
        "supply": 1.212
    }, 
    "order_6": {
        "to": 6, 
        "from": 37, 
        "supply": 5.403
    }, 
    "order_7": {
        "to": 45, 
        "from": 24, 
        "supply": 8.92
    }, 
    "order_4": {
        "to": 48, 
        "from": 11, 
        "supply": 9.341
    }, 
    "order_5": {
        "to": 34, 
        "from": 36, 
        "supply": 4.702
    }, 
    "order_105": {
        "to": 10, 
        "from": 15, 
        "supply": 1.575
    }, 
    "order_104": {
        "to": 28, 
        "from": 20, 
        "supply": 1.231
    }, 
    "order_8": {
        "to": 41, 
        "from": 1, 
        "supply": 8.076
    }, 
    "order_9": {
        "to": 42, 
        "from": 29, 
        "supply": 2.613
    }, 
    "order_101": {
        "to": 28, 
        "from": 3, 
        "supply": 5.581
    }, 
    "order_100": {
        "to": 39, 
        "from": 5, 
        "supply": 3.618
    }, 
    "order_103": {
        "to": 27, 
        "from": 48, 
        "supply": 7.916
    }, 
    "order_102": {
        "to": 27, 
        "from": 20, 
        "supply": 8.88
    }, 
    "order_285": {
        "to": 10, 
        "from": 30, 
        "supply": 7.122
    }, 
    "order_266": {
        "to": 1, 
        "from": 34, 
        "supply": 9.936
    }, 
    "order_278": {
        "to": 39, 
        "from": 1, 
        "supply": 7.41
    }, 
    "order_267": {
        "to": 4, 
        "from": 41, 
        "supply": 5.624
    }, 
    "order_239": {
        "to": 26, 
        "from": 49, 
        "supply": 2.515
    }, 
    "order_185": {
        "to": 41, 
        "from": 30, 
        "supply": 3.898
    }, 
    "order_184": {
        "to": 27, 
        "from": 21, 
        "supply": 7.29
    }, 
    "order_187": {
        "to": 31, 
        "from": 35, 
        "supply": 6.223
    }, 
    "order_186": {
        "to": 23, 
        "from": 28, 
        "supply": 2.806
    }, 
    "order_181": {
        "to": 35, 
        "from": 36, 
        "supply": 2.961
    }, 
    "order_180": {
        "to": 16, 
        "from": 24, 
        "supply": 5.004
    }, 
    "order_183": {
        "to": 23, 
        "from": 0, 
        "supply": 3.232
    }, 
    "order_182": {
        "to": 44, 
        "from": 33, 
        "supply": 6.554
    }, 
    "order_295": {
        "to": 15, 
        "from": 11, 
        "supply": 1.218
    }, 
    "order_109": {
        "to": 22, 
        "from": 29, 
        "supply": 2.969
    }, 
    "order_189": {
        "to": 40, 
        "from": 47, 
        "supply": 3.085
    }, 
    "order_188": {
        "to": 42, 
        "from": 8, 
        "supply": 2.238
    }, 
    "order_224": {
        "to": 32, 
        "from": 38, 
        "supply": 1.632
    }, 
    "order_108": {
        "to": 18, 
        "from": 41, 
        "supply": 4.663
    }, 
    "order_61": {
        "to": 15, 
        "from": 38, 
        "supply": 6.189
    }, 
    "order_60": {
        "to": 42, 
        "from": 23, 
        "supply": 3.733
    }, 
    "order_63": {
        "to": 41, 
        "from": 40, 
        "supply": 5.513
    }, 
    "order_62": {
        "to": 41, 
        "from": 8, 
        "supply": 7.44
    }, 
    "order_65": {
        "to": 2, 
        "from": 30, 
        "supply": 4.577
    }, 
    "order_64": {
        "to": 7, 
        "from": 0, 
        "supply": 3.847
    }, 
    "order_67": {
        "to": 7, 
        "from": 14, 
        "supply": 4.15
    }, 
    "order_66": {
        "to": 40, 
        "from": 7, 
        "supply": 6.147
    }, 
    "order_69": {
        "to": 1, 
        "from": 0, 
        "supply": 6.541
    }, 
    "order_68": {
        "to": 11, 
        "from": 19, 
        "supply": 8.767
    }, 
    "order_233": {
        "to": 34, 
        "from": 23, 
        "supply": 1.649
    }, 
    "order_228": {
        "to": 31, 
        "from": 46, 
        "supply": 6.699
    }, 
    "order_229": {
        "to": 19, 
        "from": 40, 
        "supply": 9.921
    }, 
    "order_118": {
        "to": 46, 
        "from": 32, 
        "supply": 9.109
    }, 
    "order_119": {
        "to": 2, 
        "from": 37, 
        "supply": 7.725
    }, 
    "order_116": {
        "to": 30, 
        "from": 3, 
        "supply": 1.912
    }, 
    "order_117": {
        "to": 2, 
        "from": 43, 
        "supply": 3.957
    }, 
    "order_114": {
        "to": 28, 
        "from": 40, 
        "supply": 1.604
    }, 
    "order_115": {
        "to": 4, 
        "from": 29, 
        "supply": 2.544
    }, 
    "order_112": {
        "to": 41, 
        "from": 21, 
        "supply": 5.862
    }, 
    "order_107": {
        "to": 1, 
        "from": 21, 
        "supply": 1.698
    }, 
    "order_110": {
        "to": 39, 
        "from": 25, 
        "supply": 6.843
    }, 
    "order_111": {
        "to": 0, 
        "from": 40, 
        "supply": 2.141
    }, 
    "order_106": {
        "to": 13, 
        "from": 25, 
        "supply": 8.217
    }, 
    "order_237": {
        "to": 27, 
        "from": 12, 
        "supply": 4.717
    }, 
    "order_236": {
        "to": 1, 
        "from": 5, 
        "supply": 3.657
    }, 
    "order_196": {
        "to": 8, 
        "from": 30, 
        "supply": 5.586
    }, 
    "order_197": {
        "to": 4, 
        "from": 1, 
        "supply": 2.301
    }, 
    "order_194": {
        "to": 33, 
        "from": 45, 
        "supply": 1.561
    }, 
    "order_195": {
        "to": 24, 
        "from": 40, 
        "supply": 6.026
    }, 
    "order_192": {
        "to": 0, 
        "from": 28, 
        "supply": 8.75
    }, 
    "order_193": {
        "to": 9, 
        "from": 26, 
        "supply": 6.11
    }, 
    "order_190": {
        "to": 39, 
        "from": 45, 
        "supply": 1.131
    }, 
    "order_191": {
        "to": 48, 
        "from": 31, 
        "supply": 9.199
    }, 
    "order_215": {
        "to": 14, 
        "from": 31, 
        "supply": 9.281
    }, 
    "order_226": {
        "to": 12, 
        "from": 27, 
        "supply": 7.518
    }, 
    "order_234": {
        "to": 4, 
        "from": 45, 
        "supply": 1.481
    }, 
    "order_284": {
        "to": 25, 
        "from": 16, 
        "supply": 7.767
    }, 
    "order_198": {
        "to": 24, 
        "from": 39, 
        "supply": 4.356
    }, 
    "order_199": {
        "to": 14, 
        "from": 22, 
        "supply": 4.534
    }, 
    "order_14": {
        "to": 41, 
        "from": 36, 
        "supply": 4.151
    }, 
    "order_15": {
        "to": 44, 
        "from": 19, 
        "supply": 8.675
    }, 
    "order_16": {
        "to": 40, 
        "from": 15, 
        "supply": 1.446
    }, 
    "order_17": {
        "to": 47, 
        "from": 48, 
        "supply": 1.801
    }, 
    "order_10": {
        "to": 33, 
        "from": 29, 
        "supply": 2.089
    }, 
    "order_11": {
        "to": 16, 
        "from": 14, 
        "supply": 9.763
    }, 
    "order_12": {
        "to": 27, 
        "from": 41, 
        "supply": 9.431
    }, 
    "order_13": {
        "to": 16, 
        "from": 11, 
        "supply": 5.125
    }, 
    "order_282": {
        "to": 43, 
        "from": 13, 
        "supply": 4.067
    }, 
    "order_18": {
        "to": 26, 
        "from": 17, 
        "supply": 4.803
    }, 
    "order_19": {
        "to": 15, 
        "from": 30, 
        "supply": 5.916
    }, 
    "order_283": {
        "to": 25, 
        "from": 39, 
        "supply": 4.829
    }, 
    "order_123": {
        "to": 36, 
        "from": 16, 
        "supply": 6.487
    }, 
    "order_122": {
        "to": 11, 
        "from": 17, 
        "supply": 6.852
    }, 
    "order_121": {
        "to": 24, 
        "from": 7, 
        "supply": 5.928
    }, 
    "order_120": {
        "to": 35, 
        "from": 23, 
        "supply": 9.959
    }, 
    "order_127": {
        "to": 36, 
        "from": 29, 
        "supply": 4.284
    }, 
    "order_126": {
        "to": 37, 
        "from": 4, 
        "supply": 1.808
    }, 
    "order_125": {
        "to": 31, 
        "from": 17, 
        "supply": 4.897
    }, 
    "order_124": {
        "to": 34, 
        "from": 42, 
        "supply": 5.588
    }, 
    "order_227": {
        "to": 49, 
        "from": 13, 
        "supply": 7.791
    }, 
    "order_129": {
        "to": 24, 
        "from": 13, 
        "supply": 1.438
    }, 
    "order_128": {
        "to": 38, 
        "from": 24, 
        "supply": 9.506
    }, 
    "order_281": {
        "to": 39, 
        "from": 4, 
        "supply": 5.471
    }, 
    "order_259": {
        "to": 28, 
        "from": 31, 
        "supply": 6.393
    }, 
    "order_258": {
        "to": 4, 
        "from": 38, 
        "supply": 8.525
    }, 
    "order_147": {
        "to": 45, 
        "from": 14, 
        "supply": 1.758
    }, 
    "order_221": {
        "to": 37, 
        "from": 46, 
        "supply": 1.372
    }, 
    "order_251": {
        "to": 0, 
        "from": 1, 
        "supply": 8.945
    }, 
    "order_250": {
        "to": 32, 
        "from": 41, 
        "supply": 5.309
    }, 
    "order_253": {
        "to": 49, 
        "from": 32, 
        "supply": 3.979
    }, 
    "order_146": {
        "to": 17, 
        "from": 5, 
        "supply": 3.814
    }, 
    "order_255": {
        "to": 49, 
        "from": 31, 
        "supply": 8.437
    }, 
    "order_254": {
        "to": 49, 
        "from": 27, 
        "supply": 8.611
    }, 
    "order_257": {
        "to": 11, 
        "from": 49, 
        "supply": 8.775
    }, 
    "order_256": {
        "to": 0, 
        "from": 17, 
        "supply": 5.466
    }, 
    "order_149": {
        "to": 7, 
        "from": 37, 
        "supply": 8.33
    }, 
    "order_217": {
        "to": 21, 
        "from": 42, 
        "supply": 6.936
    }, 
    "order_148": {
        "to": 37, 
        "from": 23, 
        "supply": 4.144
    }, 
    "order_275": {
        "to": 49, 
        "from": 8, 
        "supply": 6.605
    }, 
    "order_274": {
        "to": 47, 
        "from": 1, 
        "supply": 2.292
    }, 
    "order_277": {
        "to": 41, 
        "from": 28, 
        "supply": 6.665
    }, 
    "order_273": {
        "to": 42, 
        "from": 46, 
        "supply": 9.052
    }, 
    "order_232": {
        "to": 13, 
        "from": 21, 
        "supply": 9.18
    }, 
    "order_272": {
        "to": 30, 
        "from": 18, 
        "supply": 8.465
    }, 
    "order_134": {
        "to": 10, 
        "from": 24, 
        "supply": 1.095
    }, 
    "order_135": {
        "to": 40, 
        "from": 13, 
        "supply": 5.855
    }, 
    "order_136": {
        "to": 32, 
        "from": 17, 
        "supply": 5.167
    }, 
    "order_137": {
        "to": 9, 
        "from": 12, 
        "supply": 8.653
    }, 
    "order_130": {
        "to": 16, 
        "from": 32, 
        "supply": 1.44
    }, 
    "order_131": {
        "to": 34, 
        "from": 21, 
        "supply": 7.23
    }, 
    "order_132": {
        "to": 47, 
        "from": 46, 
        "supply": 5.02
    }, 
    "order_133": {
        "to": 39, 
        "from": 40, 
        "supply": 5.174
    }, 
    "order_270": {
        "to": 46, 
        "from": 13, 
        "supply": 8.39
    }, 
    "order_138": {
        "to": 7, 
        "from": 28, 
        "supply": 9.424
    }, 
    "order_139": {
        "to": 39, 
        "from": 13, 
        "supply": 4.723
    }, 
    "order_298": {
        "to": 34, 
        "from": 40, 
        "supply": 2.621
    }, 
    "order_248": {
        "to": 29, 
        "from": 46, 
        "supply": 7.961
    }, 
    "order_249": {
        "to": 14, 
        "from": 1, 
        "supply": 1.125
    }, 
    "order_98": {
        "to": 27, 
        "from": 26, 
        "supply": 3.806
    }, 
    "order_99": {
        "to": 43, 
        "from": 24, 
        "supply": 5.922
    }, 
    "order_286": {
        "to": 9, 
        "from": 13, 
        "supply": 3.941
    }, 
    "order_94": {
        "to": 13, 
        "from": 9, 
        "supply": 8.446
    }, 
    "order_95": {
        "to": 31, 
        "from": 19, 
        "supply": 5.722
    }, 
    "order_96": {
        "to": 5, 
        "from": 18, 
        "supply": 6.694
    }, 
    "order_97": {
        "to": 3, 
        "from": 8, 
        "supply": 1.966
    }, 
    "order_90": {
        "to": 39, 
        "from": 47, 
        "supply": 8.329
    }, 
    "order_91": {
        "to": 4, 
        "from": 11, 
        "supply": 1.288
    }, 
    "order_92": {
        "to": 35, 
        "from": 33, 
        "supply": 3.284
    }, 
    "order_93": {
        "to": 27, 
        "from": 18, 
        "supply": 4.589
    }, 
    "order_213": {
        "to": 47, 
        "from": 17, 
        "supply": 7.431
    }, 
    "order_294": {
        "to": 7, 
        "from": 17, 
        "supply": 7.567
    }, 
    "order_271": {
        "to": 41, 
        "from": 5, 
        "supply": 8.003
    }, 
    "order_297": {
        "to": 8, 
        "from": 29, 
        "supply": 7.273
    }, 
    "order_296": {
        "to": 0, 
        "from": 30, 
        "supply": 7.408
    }, 
    "order_261": {
        "to": 33, 
        "from": 14, 
        "supply": 9.566
    }, 
    "order_230": {
        "to": 20, 
        "from": 42, 
        "supply": 9.59
    }, 
    "order_291": {
        "to": 23, 
        "from": 15, 
        "supply": 5.087
    }, 
    "order_292": {
        "to": 4, 
        "from": 46, 
        "supply": 6.286
    }, 
    "order_290": {
        "to": 41, 
        "from": 13, 
        "supply": 7.088
    }, 
    "order_293": {
        "to": 5, 
        "from": 32, 
        "supply": 6.087
    }, 
    "order_280": {
        "to": 32, 
        "from": 8, 
        "supply": 1.764
    }, 
    "order_238": {
        "to": 11, 
        "from": 42, 
        "supply": 7.532
    }, 
    "order_141": {
        "to": 32, 
        "from": 7, 
        "supply": 9.748
    }, 
    "order_140": {
        "to": 15, 
        "from": 5, 
        "supply": 3.764
    }, 
    "order_143": {
        "to": 33, 
        "from": 6, 
        "supply": 1.439
    }, 
    "order_142": {
        "to": 37, 
        "from": 2, 
        "supply": 6.801
    }, 
    "order_145": {
        "to": 6, 
        "from": 3, 
        "supply": 5.852
    }, 
    "order_144": {
        "to": 48, 
        "from": 38, 
        "supply": 6.675
    }, 
    "order_89": {
        "to": 11, 
        "from": 4, 
        "supply": 1.879
    }, 
    "order_88": {
        "to": 48, 
        "from": 4, 
        "supply": 6.012
    }, 
    "order_87": {
        "to": 18, 
        "from": 48, 
        "supply": 4.866
    }, 
    "order_86": {
        "to": 10, 
        "from": 38, 
        "supply": 4.537
    }, 
    "order_85": {
        "to": 28, 
        "from": 36, 
        "supply": 9.619
    }, 
    "order_84": {
        "to": 33, 
        "from": 47, 
        "supply": 9.539
    }, 
    "order_83": {
        "to": 19, 
        "from": 49, 
        "supply": 9.278
    }, 
    "order_82": {
        "to": 4, 
        "from": 19, 
        "supply": 3.37
    }, 
    "order_81": {
        "to": 22, 
        "from": 31, 
        "supply": 5.295
    }, 
    "order_80": {
        "to": 9, 
        "from": 33, 
        "supply": 3.493
    }, 
    "order_242": {
        "to": 49, 
        "from": 21, 
        "supply": 7.486
    }, 
    "order_252": {
        "to": 43, 
        "from": 8, 
        "supply": 5.441
    }, 
    "order_243": {
        "to": 11, 
        "from": 45, 
        "supply": 6.743
    }, 
    "order_231": {
        "to": 16, 
        "from": 42, 
        "supply": 1.402
    }, 
    "order_240": {
        "to": 25, 
        "from": 8, 
        "supply": 7.949
    }
}